RevelZhongwenWendang/README.md
RevelZhongwenWendang/__init__.py
RevelZhongwenWendang/__main__.py
RevelZhongwenWendang/file.epub
RevelZhongwenWendang/index.html
RevelZhongwenWendang/css/__init__.py
RevelZhongwenWendang/css/annotations.css
RevelZhongwenWendang/css/main.css
RevelZhongwenWendang/css/normalize.css
RevelZhongwenWendang/css/popup.css
RevelZhongwenWendang/font/__init__.py
RevelZhongwenWendang/font/fontello.eot
RevelZhongwenWendang/font/fontello.svg
RevelZhongwenWendang/font/fontello.ttf
RevelZhongwenWendang/font/fontello.woff
RevelZhongwenWendang/img/__init__.py
RevelZhongwenWendang/img/annotator-glyph-sprite.png
RevelZhongwenWendang/img/annotator-icon-sprite.png
RevelZhongwenWendang/img/apple-touch-icon.png
RevelZhongwenWendang/img/cancelfullscreen.png
RevelZhongwenWendang/img/close.png
RevelZhongwenWendang/img/fullscreen.png
RevelZhongwenWendang/img/loader.gif
RevelZhongwenWendang/img/menu-icon.png
RevelZhongwenWendang/img/save.png
RevelZhongwenWendang/img/saved.png
RevelZhongwenWendang/img/settings-s.png
RevelZhongwenWendang/img/settings.png
RevelZhongwenWendang/img/star.png
RevelZhongwenWendang/js/__init__.py
RevelZhongwenWendang/js/epub.js
RevelZhongwenWendang/js/epub.min.js
RevelZhongwenWendang/js/epub.min.map
RevelZhongwenWendang/js/hooks.min.js
RevelZhongwenWendang/js/hooks.min.map
RevelZhongwenWendang/js/reader.js
RevelZhongwenWendang/js/reader.js.map
RevelZhongwenWendang/js/reader.min.js
RevelZhongwenWendang/js/reader.min.map
RevelZhongwenWendang/js/hooks/__init__.py
RevelZhongwenWendang/js/hooks/extensions/__init__.py
RevelZhongwenWendang/js/hooks/extensions/highlight.js
RevelZhongwenWendang/js/libs/__init__.py
RevelZhongwenWendang/js/libs/jquery.min.js
RevelZhongwenWendang/js/libs/localforage.min.js
RevelZhongwenWendang/js/libs/screenfull.js
RevelZhongwenWendang/js/libs/screenfull.min.js
RevelZhongwenWendang/js/libs/zip.min.js
RevelZhongwenWendang/js/plugins/__init__.py
RevelZhongwenWendang/js/plugins/hypothesis.js
revel_zhongwen_wendang-2024.3.2.0.dist-info/METADATA
revel_zhongwen_wendang-2024.3.2.0.dist-info/WHEEL
revel_zhongwen_wendang-2024.3.2.0.dist-info/entry_points.txt
revel_zhongwen_wendang-2024.3.2.0.dist-info/top_level.txt
revel_zhongwen_wendang-2024.3.2.0.dist-info/RECORD
